Metadata-Version: 2.1
Name: dgcnn
Version: 0.3.1
Summary: TensorFlow 2 implementation of Deep Graph Convolutional Neural Networks.
Home-page: https://github.com/LeviBorodenko/dgcnn
Author: Levi Borodenko
Author-email: Levi.borodenko@gmail.com
License: mit
Project-URL: Documentation, https://dgcnn.readthedocs.io/
Platform: any
Classifier: Development Status :: 4 - Beta
Classifier: Programming Language :: Python
Provides-Extra: testing
